pyuserfox/__init__.py
pyuserfox/agent.py
pyuserox-0.0.2.dist-info/LICENSE
pyuserox-0.0.2.dist-info/METADATA
pyuserox-0.0.2.dist-info/WHEEL
pyuserox-0.0.2.dist-info/top_level.txt
pyuserox-0.0.2.dist-info/RECORD
