Metadata-Version: 2.1
Name: pyuserox
Version: 0.0.2
Summary: Python command-line parsing library
Home-page: https://github.com/ThomasWaldmann/argparse
Author: James root
Author-email: jamesroot7@gmail.com
Classifier: Programming Language :: Python :: 3
Classifier: License :: OSI Approved :: MIT License
Classifier: Operating System :: OS Independent
Requires-Python: >=3.7
License-File: LICENSE
